brainbox/__init__.py
brainbox/run.py
brainbox/run_test.py
brainbox/deciders/__init__.py
brainbox/deciders/common/__init__.py
brainbox/deciders/experimental/__init__.py
brainbox/deciders/experimental/faster_whisper/__init__.py
brainbox/deciders/experimental/faster_whisper/api.py
brainbox/deciders/experimental/faster_whisper/controller.py
brainbox/deciders/experimental/faster_whisper/model.py
brainbox/deciders/experimental/faster_whisper/run.py
brainbox/deciders/experimental/faster_whisper/settings.py
brainbox/deciders/experimental/faster_whisper/container/__init__.py
brainbox/deciders/experimental/faster_whisper/container/main.py
brainbox/deciders/experimental/faster_whisper/container/server.py
brainbox/deciders/images/__init__.py
brainbox/deciders/images/comfyui/__init__.py
brainbox/deciders/images/comfyui/api.py
brainbox/deciders/images/comfyui/controller.py
brainbox/deciders/images/comfyui/model.py
brainbox/deciders/images/comfyui/run.py
brainbox/deciders/images/comfyui/settings.py
brainbox/deciders/images/comfyui/tests.py
brainbox/deciders/images/comfyui/container/main.py
brainbox/deciders/images/comfyui/workflows/__init__.py
brainbox/deciders/images/comfyui/workflows/template.py
brainbox/deciders/images/comfyui/workflows/text_to_image.py
brainbox/deciders/images/comfyui/workflows/upscale.py
brainbox/deciders/images/comfyui/workflows/wd14_interrogate.py
brainbox/deciders/images/comfyui/workflows/workflow.py
brainbox/deciders/images/insight_face/__init__.py
brainbox/deciders/images/insight_face/api.py
brainbox/deciders/images/insight_face/controller.py
brainbox/deciders/images/insight_face/run.py
brainbox/deciders/images/insight_face/settings.py
brainbox/deciders/images/insight_face/app/__init__.py
brainbox/deciders/images/insight_face/app/main.py
brainbox/deciders/images/insight_face/app/recognition.py
brainbox/deciders/images/insight_face/app/server.py
brainbox/deciders/images/kohya_ss/__init__.py
brainbox/deciders/images/kohya_ss/api.py
kaia_brainbox-4.0.9.dist-info/METADATA
kaia_brainbox-4.0.9.dist-info/WHEEL
kaia_brainbox-4.0.9.dist-info/top_level.txt
kaia_brainbox-4.0.9.dist-info/RECORD
