Metadata-Version: 2.4
Name: kaia-brainbox
Version: 4.0.9
Summary: Web-server and API to access the curated set of AI-deciders, packaged as containers
Author-email: Yuri Okulovsky <yuri.okulovsky@gmail.com>
License-Expression: LGPL-3.0-or-later
Project-URL: repository, https://github.com/okulovsky/kaia/tree/main/brainbox
Classifier: Programming Language :: Python :: 3.10
Classifier: Programming Language :: Python :: 3.11
Classifier: Programming Language :: Python :: 3.12
Classifier: Programming Language :: Python :: 3.13
Classifier: Intended Audience :: Developers
Classifier: Intended Audience :: Science/Research
Classifier: Intended Audience :: Information Technology
Classifier: Topic :: Scientific/Engineering :: Artificial Intelligence
Classifier: Development Status :: 4 - Beta
Requires-Python: <4.0,>=3.10
Requires-Dist: yo_fluq
Requires-Dist: flask
Requires-Dist: requests
Requires-Dist: sqlalchemy
Requires-Dist: soundfile
Requires-Dist: kaia-foundation
Requires-Dist: toml
Requires-Dist: pandas
Requires-Dist: huggingface_hub
Requires-Dist: dill
Provides-Extra: dev
Requires-Dist: tox; extra == "dev"
Requires-Dist: tox-conda; extra == "dev"
Requires-Dist: twine; extra == "dev"
